singletrader/__init__.py
singletrader/constant.py
singletrader/backtesting/__init__.py
singletrader/backtesting/account.py
singletrader/backtesting/bar.py
singletrader/backtesting/engine.py
singletrader/backtesting/order.py
singletrader/backtesting/position.py
singletrader/backtesting/shared.py
singletrader/backtesting/strategy.py
singletrader/datasdk/__init__.py
singletrader/datasdk/qlib/__init__.py
singletrader/datasdk/qlib/base.py
singletrader/datasdk/qlib/dump_bin.py
singletrader/datasdk/sql/__init__.py
singletrader/datasdk/sql/config.py
singletrader/datasdk/sql/dataapi.py
singletrader/datasdk/sql/dataapi_pro.py
singletrader/datasdk/sql/datasaver.py
singletrader/datasdk/sql/handler.py
singletrader/datasdk/sql/jqapi.py
singletrader/datasdk/sql/pgsql_common.py
singletrader/factorlib/__init__.py
singletrader/factorlib/factor.py
singletrader/factorlib/factortesting.py
singletrader/factorlib/functions.py
singletrader/factorlib/plotting.py
singletrader/factorlib/universe.py
singletrader/performance/__init__.py
singletrader/performance/attributor.py
singletrader/performance/common.py
singletrader/processors/__init__.py
singletrader/processors/base.py
singletrader/processors/cs_processor.py
singletrader/processors/normal_processor.py
singletrader/processors/operator.py
singletrader/processors/ts_processor.py
singletrader/scripts/__init__.py
singletrader/scripts/dump_index.py
singletrader/scripts/dump_scripts.py
singletrader/scripts/test_scripts.py
singletrader/shared/__init__.py
singletrader/shared/logging.py
singletrader/shared/utility.py
singletrader-0.2.1.dist-info/LICENSE
singletrader-0.2.1.dist-info/METADATA
singletrader-0.2.1.dist-info/WHEEL
singletrader-0.2.1.dist-info/top_level.txt
singletrader-0.2.1.dist-info/RECORD
